{
    "control": [
        {
            "VTOY_DEFAULT_SEARCH_ROOT": "/iso"
        }
    ],
    "theme": {
        "file": "/ventoy/themes/ventoy-just-black/theme.txt",
        "gfxmode": "1920x1080"
    },
    "theme_legacy": {
        "file": "/ventoy/themes/ventoy-just-black/theme_legacy.txt",
        "gfxmode": "1920x1080"
    },
    "auto_install": [
        {
            "image": "/iso/Win11_25H2_English_x64.iso",
            "template": [
                "/ventoy/scripts/autounattend.xml"
            ]
        }
    ]
}